stakemachine/__init__.py
stakemachine/basestrategy.py
stakemachine/bot.py
stakemachine/cli.py
stakemachine/errors.py
stakemachine/exceptions.py
stakemachine/statemachine.py
stakemachine/storage.py
stakemachine/ui.py
stakemachine/strategies/__init__.py
stakemachine/strategies/echo.py
stakemachine/strategies/storagedemo.py
stakemachine/strategies/walls.py
stakemachine-0.0.6.dist-info/DESCRIPTION.rst
stakemachine-0.0.6.dist-info/METADATA
stakemachine-0.0.6.dist-info/RECORD
stakemachine-0.0.6.dist-info/WHEEL
stakemachine-0.0.6.dist-info/entry_points.txt
stakemachine-0.0.6.dist-info/metadata.json
stakemachine-0.0.6.dist-info/top_level.txt
