Metadata-Version: 2.0
Name: stakemachine
Version: 0.0.6
Summary: Trading bot infrastructure for the DEX (BitShares)
Home-page: http://www.github.com/xeroc/stakemachine
Author: Fabian Schuh
Author-email: Fabian@chainsquad.com
License: UNKNOWN
Download-URL: https://github.com/xeroc/stakemachine/tarball/0.0.6
Keywords: stake,bot,trading,api,blog,blockchain
Platform: UNKNOWN
Classifier: License :: OSI Approved :: MIT License
Classifier: Operating System :: OS Independent
Classifier: Programming Language :: Python :: 3
Classifier: Development Status :: 3 - Alpha
Classifier: Intended Audience :: Developers
Requires-Dist: appdirs
Requires-Dist: bitshares (>=0.1.7)
Requires-Dist: click
Requires-Dist: click-datetime
Requires-Dist: colorama
Requires-Dist: prettytable
Requires-Dist: pyyaml
Requires-Dist: sqlalchemy
Requires-Dist: tqdm
Requires-Dist: uptick (>=0.1.4)
